Workbook

Sheet GERAL
A1: GCMIX SJE PE
A2: Competência: | B2: SETEMBRO/2026 | C2: Data: | D2: 15/09/2026 | E2: % Quinzena: | F2: 0.4
A3: 🟡 AMARELO = você digita · ⚪ CINZA = calculado sozinho (não mexa; só sobrescreva num caso especial)
A4: Nº | B4: NOME | C4: FUNÇÃO | D4: TOTAL BRUTO | E4: FILHOS (ATÉ 14) | F4: INSS | G4: FAMÍLIA | H4: IRRF | I4: QUINZENA | J4: MENSAL (LÍQUIDO) | K4: AGÊNCIA / C/C | L4: PIX | M4: OBS
A5: =IF($B5="","",ROW()-4) | B5: ARLINDO LEITE DE BRITO JUNIOR | C5: MOTORISTA | D5: 2410 | E5: 0 | F5: =IF($D5="","",ROUND(VLOOKUP(MIN($D5,TABELAS!$B$10),TABELAS!$A$5:$C$8,2,TRUE)*MIN($D5,TABELAS!$B$10)-VLOOKUP(MIN($D5,TABELAS!$B$10),TABELAS!$A$5:$C$8,3,TRUE),2)) | G5: =IF($D5="","",IF($D5>TABELAS!$B$13,0,$E5*TABELAS!$B$12)) | H5: =IF($D5="","",IF($D5<=TABELAS!$B$22,0,ROUND(MAX(0,(VLOOKUP(MAX(0.01,$D5-$F5),TABELAS!$A$16:$C$20,2,TRUE)*($D5-$F5)-VLOOKUP(MAX(0.01,$D5-$F5),TABELAS!$A$16:$C$20,3,TRUE))-IF(($D5-$F5)<=TABELAS!$B$23,MIN((VLOOKUP(MAX(0.01,$D5-$F5),TABELAS!$A$16:$C$20,2,TRUE)*($D5-$F5)-VLOOKUP(MAX(0.01,$D5-$F5),TABELAS!$A$16:$C$20,3,TRUE)),TABELAS!$B$24-TABELAS!$B$25*($D5-$F5)),0)),2))) | I5: =IF($D5="","",ROUND($D5*$F$2,2)) | J5: =IF($D5="","",ROUND($D5-$I5-$F5+$G5-$H5,2)) | L5: 87999146340
A6: =IF($B6="","",ROW()-4) | B6: CARLOS ALBERTO FERREIRA | C6: MOTORISTA | D6: 2410 | E6: 0 | F6: =IF($D6="","",ROUND(VLOOKUP(MIN($D6,TABELAS!$B$10),TABELAS!$A$5:$C$8,2,TRUE)*MIN($D6,TABELAS!$B$10)-VLOOKUP(MIN($D6,TABELAS!$B$10),TABELAS!$A$5:$C$8,3,TRUE),2)) | G6: =IF($D6="","",IF($D6>TABELAS!$B$13,0,$E6*TABELAS!$B$12)) | H6: =IF($D6="","",IF($D6<=TABELAS!$B$22,0,ROUND(MAX(0,(VLOOKUP(MAX(0.01,$D6-$F6),TABELAS!$A$16:$C$20,2,TRUE)*($D6-$F6)-VLOOKUP(MAX(0.01,$D6-$F6),TABELAS!$A$16:$C$20,3,TRUE))-IF(($D6-$F6)<=TABELAS!$B$23,MIN((VLOOKUP(MAX(0.01,$D6-$F6),TABELAS!$A$16:$C$20,2,TRUE)*($D6-$F6)-VLOOKUP(MAX(0.01,$D6-$F6),TABELAS!$A$16:$C$20,3,TRUE)),TABELAS!$B$24-TABELAS!$B$25*($D6-$F6)),0)),2))) | I6: =IF($D6="","",ROUND($D6*$F$2,2)) | J6: =IF($D6="","",ROUND($D6-$I6-$F6+$G6-$H6,2)) | K6: 1563/82316-4
A7: =IF($B7="","",ROW()-4) | B7: IRINALDO DOS SANTOS BRITO | C7: MOTORISTA | D7: 2410 | E7: 0 | F7: =IF($D7="","",ROUND(VLOOKUP(MIN($D7,TABELAS!$B$10),TABELAS!$A$5:$C$8,2,TRUE)*MIN($D7,TABELAS!$B$10)-VLOOKUP(MIN($D7,TABELAS!$B$10),TABELAS!$A$5:$C$8,3,TRUE),2)) | G7: =IF($D7="","",IF($D7>TABELAS!$B$13,0,$E7*TABELAS!$B$12)) | H7: =IF($D7="","",IF($D7<=TABELAS!$B$22,0,ROUND(MAX(0,(VLOOKUP(MAX(0.01,$D7-$F7),TABELAS!$A$16:$C$20,2,TRUE)*($D7-$F7)-VLOOKUP(MAX(0.01,$D7-$F7),TABELAS!$A$16:$C$20,3,TRUE))-IF(($D7-$F7)<=TABELAS!$B$23,MIN((VLOOKUP(MAX(0.01,$D7-$F7),TABELAS!$A$16:$C$20,2,TRUE)*($D7-$F7)-VLOOKUP(MAX(0.01,$D7-$F7),TABELAS!$A$16:$C$20,3,TRUE)),TABELAS!$B$24-TABELAS!$B$25*($D7-$F7)),0)),2))) | I7: =IF($D7="","",ROUND($D7*$F$2,2)) | J7: =IF($D7="","",ROUND($D7-$I7-$F7+$G7-$H7,2)) | K7: 1563/76509-1
A8: =IF($B8="","",ROW()-4) | B8: JOSÉ EDNALDO XAVIER SOARES | C8: AJUDANTE | D8: 1720 | E8: 1 | F8: =IF($D8="","",ROUND(VLOOKUP(MIN($D8,TABELAS!$B$10),TABELAS!$A$5:$C$8,2,TRUE)*MIN($D8,TABELAS!$B$10)-VLOOKUP(MIN($D8,TABELAS!$B$10),TABELAS!$A$5:$C$8,3,TRUE),2)) | G8: =IF($D8="","",IF($D8>TABELAS!$B$13,0,$E8*TABELAS!$B$12)) | H8: =IF($D8="","",IF($D8<=TABELAS!$B$22,0,ROUND(MAX(0,(VLOOKUP(MAX(0.01,$D8-$F8),TABELAS!$A$16:$C$20,2,TRUE)*($D8-$F8)-VLOOKUP(MAX(0.01,$D8-$F8),TABELAS!$A$16:$C$20,3,TRUE))-IF(($D8-$F8)<=TABELAS!$B$23,MIN((VLOOKUP(MAX(0.01,$D8-$F8),TABELAS!$A$16:$C$20,2,TRUE)*($D8-$F8)-VLOOKUP(MAX(0.01,$D8-$F8),TABELAS!$A$16:$C$20,3,TRUE)),TABELAS!$B$24-TABELAS!$B$25*($D8-$F8)),0)),2))) | I8: =IF($D8="","",ROUND($D8*$F$2,2)) | J8: =IF($D8="","",ROUND($D8-$I8-$F8+$G8-$H8,2)) | K8: 3506/336083-1
A9: =IF($B9="","",ROW()-4) | B9: JOSE PEDRO DA SILVA | C9: AJUDANTE | D9: 1720 | E9: 2 | F9: =IF($D9="","",ROUND(VLOOKUP(MIN($D9,TABELAS!$B$10),TABELAS!$A$5:$C$8,2,TRUE)*MIN($D9,TABELAS!$B$10)-VLOOKUP(MIN($D9,TABELAS!$B$10),TABELAS!$A$5:$C$8,3,TRUE),2)) | G9: =IF($D9="","",IF($D9>TABELAS!$B$13,0,$E9*TABELAS!$B$12)) | H9: =IF($D9="","",IF($D9<=TABELAS!$B$22,0,ROUND(MAX(0,(VLOOKUP(MAX(0.01,$D9-$F9),TABELAS!$A$16:$C$20,2,TRUE)*($D9-$F9)-VLOOKUP(MAX(0.01,$D9-$F9),TABELAS!$A$16:$C$20,3,TRUE))-IF(($D9-$F9)<=TABELAS!$B$23,MIN((VLOOKUP(MAX(0.01,$D9-$F9),TABELAS!$A$16:$C$20,2,TRUE)*($D9-$F9)-VLOOKUP(MAX(0.01,$D9-$F9),TABELAS!$A$16:$C$20,3,TRUE)),TABELAS!$B$24-TABELAS!$B$25*($D9-$F9)),0)),2))) | I9: =IF($D9="","",ROUND($D9*$F$2,2)) | J9: =IF($D9="","",ROUND($D9-$I9-$F9+$G9-$H9,2)) | L9: 87996349221
A10: =IF($B10="","",ROW()-4) | B10: JOSÉ EUGENIO BRITO ALVES | C10: MOTORISTA | D10: 2410 | E10: 0 | F10: =IF($D10="","",ROUND(VLOOKUP(MIN($D10,TABELAS!$B$10),TABELAS!$A$5:$C$8,2,TRUE)*MIN($D10,TABELAS!$B$10)-VLOOKUP(MIN($D10,TABELAS!$B$10),TABELAS!$A$5:$C$8,3,TRUE),2)) | G10: =IF($D10="","",IF($D10>TABELAS!$B$13,0,$E10*TABELAS!$B$12)) | H10: =IF($D10="","",IF($D10<=TABELAS!$B$22,0,ROUND(MAX(0,(VLOOKUP(MAX(0.01,$D10-$F10),TABELAS!$A$16:$C$20,2,TRUE)*($D10-$F10)-VLOOKUP(MAX(0.01,$D10-$F10),TABELAS!$A$16:$C$20,3,TRUE))-IF(($D10-$F10)<=TABELAS!$B$23,MIN((VLOOKUP(MAX(0.01,$D10-$F10),TABELAS!$A$16:$C$20,2,TRUE)*($D10-$F10)-VLOOKUP(MAX(0.01,$D10-$F10),TABELAS!$A$16:$C$20,3,TRUE)),TABELAS!$B$24-TABELAS!$B$25*($D10-$F10)),0)),2))) | I10: =IF($D10="","",ROUND($D10*$F$2,2)) | J10: =IF($D10="","",ROUND($D10-$I10-$F10+$G10-$H10,2)) | K10: 6240/255425-10
A11: =IF($B11="","",ROW()-4) | B11: JOSÉ ILTON LACERDA R. JUNIOR | C11: MOTORISTA BOMBISTA | D11: 2520 | E11: 0 | F11: =IF($D11="","",ROUND(VLOOKUP(MIN($D11,TABELAS!$B$10),TABELAS!$A$5:$C$8,2,TRUE)*MIN($D11,TABELAS!$B$10)-VLOOKUP(MIN($D11,TABELAS!$B$10),TABELAS!$A$5:$C$8,3,TRUE),2)) | G11: =IF($D11="","",IF($D11>TABELAS!$B$13,0,$E11*TABELAS!$B$12)) | H11: =IF($D11="","",IF($D11<=TABELAS!$B$22,0,ROUND(MAX(0,(VLOOKUP(MAX(0.01,$D11-$F11),TABELAS!$A$16:$C$20,2,TRUE)*($D11-$F11)-VLOOKUP(MAX(0.01,$D11-$F11),TABELAS!$A$16:$C$20,3,TRUE))-IF(($D11-$F11)<=TABELAS!$B$23,MIN((VLOOKUP(MAX(0.01,$D11-$F11),TABELAS!$A$16:$C$20,2,TRUE)*($D11-$F11)-VLOOKUP(MAX(0.01,$D11-$F11),TABELAS!$A$16:$C$20,3,TRUE)),TABELAS!$B$24-TABELAS!$B$25*($D11-$F11)),0)),2))) | I11: =IF($D11="","",ROUND($D11*$F$2,2)) | J11: =IF($D11="","",ROUND($D11-$I11-$F11+$G11-$H11,2)) | K11: 1563/52004-8
A12: =IF($B12="","",ROW()-4) | B12: JOSÉ MARINALDO PEREIRA DE ARAÚJO | C12: BALANCEIRO | D12: 2520 | E12: 0 | F12: =IF($D12="","",ROUND(VLOOKUP(MIN($D12,TABELAS!$B$10),TABELAS!$A$5:$C$8,2,TRUE)*MIN($D12,TABELAS!$B$10)-VLOOKUP(MIN($D12,TABELAS!$B$10),TABELAS!$A$5:$C$8,3,TRUE),2)) | G12: =IF($D12="","",IF($D12>TABELAS!$B$13,0,$E12*TABELAS!$B$12)) | H12: =IF($D12="","",IF($D12<=TABELAS!$B$22,0,ROUND(MAX(0,(VLOOKUP(MAX(0.01,$D12-$F12),TABELAS!$A$16:$C$20,2,TRUE)*($D12-$F12)-VLOOKUP(MAX(0.01,$D12-$F12),TABELAS!$A$16:$C$20,3,TRUE))-IF(($D12-$F12)<=TABELAS!$B$23,MIN((VLOOKUP(MAX(0.01,$D12-$F12),TABELAS!$A$16:$C$20,2,TRUE)*($D12-$F12)-VLOOKUP(MAX(0.01,$D12-$F12),TABELAS!$A$16:$C$20,3,TRUE)),TABELAS!$B$24-TABELAS!$B$25*($D12-$F12)),0)),2))) | I12: =IF($D12="","",ROUND($D12*$F$2,2)) | J12: =IF($D12="","",ROUND($D12-$I12-$F12+$G12-$H12,2)) | K12: 6240/251525-4
A13: =IF($B13="","",ROW()-4) | B13: PATRÍCIA DE LIMA GONÇALVES | C13: SECRETARIA | D13: 2080 | E13: 0 | F13: =IF($D13="","",ROUND(VLOOKUP(MIN($D13,TABELAS!$B$10),TABELAS!$A$5:$C$8,2,TRUE)*MIN($D13,TABELAS!$B$10)-VLOOKUP(MIN($D13,TABELAS!$B$10),TABELAS!$A$5:$C$8,3,TRUE),2)) | G13: =IF($D13="","",IF($D13>TABELAS!$B$13,0,$E13*TABELAS!$B$12)) | H13: =IF($D13="","",IF($D13<=TABELAS!$B$22,0,ROUND(MAX(0,(VLOOKUP(MAX(0.01,$D13-$F13),TABELAS!$A$16:$C$20,2,TRUE)*($D13-$F13)-VLOOKUP(MAX(0.01,$D13-$F13),TABELAS!$A$16:$C$20,3,TRUE))-IF(($D13-$F13)<=TABELAS!$B$23,MIN((VLOOKUP(MAX(0.01,$D13-$F13),TABELAS!$A$16:$C$20,2,TRUE)*($D13-$F13)-VLOOKUP(MAX(0.01,$D13-$F13),TABELAS!$A$16:$C$20,3,TRUE)),TABELAS!$B$24-TABELAS!$B$25*($D13-$F13)),0)),2))) | I13: =IF($D13="","",ROUND($D13*$F$2,2)) | J13: =IF($D13="","",ROUND($D13-$I13-$F13+$G13-$H13,2)) | K13: 6045/7335-1
A14: =IF($B14="","",ROW()-4) | B14: VALDERCLEITON FREIRE DE OLIVEIRA | C14: VENDEDOR | D14: 2520 | E14: 0 | F14: =IF($D14="","",ROUND(VLOOKUP(MIN($D14,TABELAS!$B$10),TABELAS!$A$5:$C$8,2,TRUE)*MIN($D14,TABELAS!$B$10)-VLOOKUP(MIN($D14,TABELAS!$B$10),TABELAS!$A$5:$C$8,3,TRUE),2)) | G14: =IF($D14="","",IF($D14>TABELAS!$B$13,0,$E14*TABELAS!$B$12)) | H14: =IF($D14="","",IF($D14<=TABELAS!$B$22,0,ROUND(MAX(0,(VLOOKUP(MAX(0.01,$D14-$F14),TABELAS!$A$16:$C$20,2,TRUE)*($D14-$F14)-VLOOKUP(MAX(0.01,$D14-$F14),TABELAS!$A$16:$C$20,3,TRUE))-IF(($D14-$F14)<=TABELAS!$B$23,MIN((VLOOKUP(MAX(0.01,$D14-$F14),TABELAS!$A$16:$C$20,2,TRUE)*($D14-$F14)-VLOOKUP(MAX(0.01,$D14-$F14),TABELAS!$A$16:$C$20,3,TRUE)),TABELAS!$B$24-TABELAS!$B$25*($D14-$F14)),0)),2))) | I14: =IF($D14="","",ROUND($D14*$F$2,2)) | J14: =IF($D14="","",ROUND($D14-$I14-$F14+$G14-$H14,2)) | K14: 6347/396600-4 | M14: Comissão de vendas na aba VENDAS
A15: =IF($B15="","",ROW()-4) | B15: RENILSON FERREIRA DE MELO | C15: ENG. ELETRICO | D15: 9000 | E15: 0 | F15: =IF($D15="","",ROUND(VLOOKUP(MIN($D15,TABELAS!$B$10),TABELAS!$A$5:$C$8,2,TRUE)*MIN($D15,TABELAS!$B$10)-VLOOKUP(MIN($D15,TABELAS!$B$10),TABELAS!$A$5:$C$8,3,TRUE),2)) | G15: =IF($D15="","",IF($D15>TABELAS!$B$13,0,$E15*TABELAS!$B$12)) | H15: =IF($D15="","",IF($D15<=TABELAS!$B$22,0,ROUND(MAX(0,(VLOOKUP(MAX(0.01,$D15-$F15),TABELAS!$A$16:$C$20,2,TRUE)*($D15-$F15)-VLOOKUP(MAX(0.01,$D15-$F15),TABELAS!$A$16:$C$20,3,TRUE))-IF(($D15-$F15)<=TABELAS!$B$23,MIN((VLOOKUP(MAX(0.01,$D15-$F15),TABELAS!$A$16:$C$20,2,TRUE)*($D15-$F15)-VLOOKUP(MAX(0.01,$D15-$F15),TABELAS!$A$16:$C$20,3,TRUE)),TABELAS!$B$24-TABELAS!$B$25*($D15-$F15)),0)),2))) | I15: =IF($D15="","",ROUND($D15*$F$2,2)) | J15: =IF($D15="","",ROUND($D15-$I15-$F15+$G15-$H15,2)) | M15: Paga IR a partir de 2026 (Lei 15.270)
A16: =IF($B16="","",ROW()-4) | F16: =IF($D16="","",ROUND(VLOOKUP(MIN($D16,TABELAS!$B$10),TABELAS!$A$5:$C$8,2,TRUE)*MIN($D16,TABELAS!$B$10)-VLOOKUP(MIN($D16,TABELAS!$B$10),TABELAS!$A$5:$C$8,3,TRUE),2)) | G16: =IF($D16="","",IF($D16>TABELAS!$B$13,0,$E16*TABELAS!$B$12)) | H16: =IF($D16="","",IF($D16<=TABELAS!$B$22,0,ROUND(MAX(0,(VLOOKUP(MAX(0.01,$D16-$F16),TABELAS!$A$16:$C$20,2,TRUE)*($D16-$F16)-VLOOKUP(MAX(0.01,$D16-$F16),TABELAS!$A$16:$C$20,3,TRUE))-IF(($D16-$F16)<=TABELAS!$B$23,MIN((VLOOKUP(MAX(0.01,$D16-$F16),TABELAS!$A$16:$C$20,2,TRUE)*($D16-$F16)-VLOOKUP(MAX(0.01,$D16-$F16),TABELAS!$A$16:$C$20,3,TRUE)),TABELAS!$B$24-TABELAS!$B$25*($D16-$F16)),0)),2))) | I16: =IF($D16="","",ROUND($D16*$F$2,2)) | J16: =IF($D16="","",ROUND($D16-$I16-$F16+$G16-$H16,2))
A17: =IF($B17="","",ROW()-4) | F17: =IF($D17="","",ROUND(VLOOKUP(MIN($D17,TABELAS!$B$10),TABELAS!$A$5:$C$8,2,TRUE)*MIN($D17,TABELAS!$B$10)-VLOOKUP(MIN($D17,TABELAS!$B$10),TABELAS!$A$5:$C$8,3,TRUE),2)) | G17: =IF($D17="","",IF($D17>TABELAS!$B$13,0,$E17*TABELAS!$B$12)) | H17: =IF($D17="","",IF($D17<=TABELAS!$B$22,0,ROUND(MAX(0,(VLOOKUP(MAX(0.01,$D17-$F17),TABELAS!$A$16:$C$20,2,TRUE)*($D17-$F17)-VLOOKUP(MAX(0.01,$D17-$F17),TABELAS!$A$16:$C$20,3,TRUE))-IF(($D17-$F17)<=TABELAS!$B$23,MIN((VLOOKUP(MAX(0.01,$D17-$F17),TABELAS!$A$16:$C$20,2,TRUE)*($D17-$F17)-VLOOKUP(MAX(0.01,$D17-$F17),TABELAS!$A$16:$C$20,3,TRUE)),TABELAS!$B$24-TABELAS!$B$25*($D17-$F17)),0)),2))) | I17: =IF($D17="","",ROUND($D17*$F$2,2)) | J17: =IF($D17="","",ROUND($D17-$I17-$F17+$G17-$H17,2))
A18: =IF($B18="","",ROW()-4) | F18: =IF($D18="","",ROUND(VLOOKUP(MIN($D18,TABELAS!$B$10),TABELAS!$A$5:$C$8,2,TRUE)*MIN($D18,TABELAS!$B$10)-VLOOKUP(MIN($D18,TABELAS!$B$10),TABELAS!$A$5:$C$8,3,TRUE),2)) | G18: =IF($D18="","",IF($D18>TABELAS!$B$13,0,$E18*TABELAS!$B$12)) | H18: =IF($D18="","",IF($D18<=TABELAS!$B$22,0,ROUND(MAX(0,(VLOOKUP(MAX(0.01,$D18-$F18),TABELAS!$A$16:$C$20,2,TRUE)*($D18-$F18)-VLOOKUP(MAX(0.01,$D18-$F18),TABELAS!$A$16:$C$20,3,TRUE))-IF(($D18-$F18)<=TABELAS!$B$23,MIN((VLOOKUP(MAX(0.01,$D18-$F18),TABELAS!$A$16:$C$20,2,TRUE)*($D18-$F18)-VLOOKUP(MAX(0.01,$D18-$F18),TABELAS!$A$16:$C$20,3,TRUE)),TABELAS!$B$24-TABELAS!$B$25*($D18-$F18)),0)),2))) | I18: =IF($D18="","",ROUND($D18*$F$2,2)) | J18: =IF($D18="","",ROUND($D18-$I18-$F18+$G18-$H18,2))
A19: =IF($B19="","",ROW()-4) | F19: =IF($D19="","",ROUND(VLOOKUP(MIN($D19,TABELAS!$B$10),TABELAS!$A$5:$C$8,2,TRUE)*MIN($D19,TABELAS!$B$10)-VLOOKUP(MIN($D19,TABELAS!$B$10),TABELAS!$A$5:$C$8,3,TRUE),2)) | G19: =IF($D19="","",IF($D19>TABELAS!$B$13,0,$E19*TABELAS!$B$12)) | H19: =IF($D19="","",IF($D19<=TABELAS!$B$22,0,ROUND(MAX(0,(VLOOKUP(MAX(0.01,$D19-$F19),TABELAS!$A$16:$C$20,2,TRUE)*($D19-$F19)-VLOOKUP(MAX(0.01,$D19-$F19),TABELAS!$A$16:$C$20,3,TRUE))-IF(($D19-$F19)<=TABELAS!$B$23,MIN((VLOOKUP(MAX(0.01,$D19-$F19),TABELAS!$A$16:$C$20,2,TRUE)*($D19-$F19)-VLOOKUP(MAX(0.01,$D19-$F19),TABELAS!$A$16:$C$20,3,TRUE)),TABELAS!$B$24-TABELAS!$B$25*($D19-$F19)),0)),2))) | I19: =IF($D19="","",ROUND($D19*$F$2,2)) | J19: =IF($D19="","",ROUND($D19-$I19-$F19+$G19-$H19,2))
A20: =IF($B20="","",ROW()-4) | F20: =IF($D20="","",ROUND(VLOOKUP(MIN($D20,TABELAS!$B$10),TABELAS!$A$5:$C$8,2,TRUE)*MIN($D20,TABELAS!$B$10)-VLOOKUP(MIN($D20,TABELAS!$B$10),TABELAS!$A$5:$C$8,3,TRUE),2)) | G20: =IF($D20="","",IF($D20>TABELAS!$B$13,0,$E20*TABELAS!$B$12)) | H20: =IF($D20="","",IF($D20<=TABELAS!$B$22,0,ROUND(MAX(0,(VLOOKUP(MAX(0.01,$D20-$F20),TABELAS!$A$16:$C$20,2,TRUE)*($D20-$F20)-VLOOKUP(MAX(0.01,$D20-$F20),TABELAS!$A$16:$C$20,3,TRUE))-IF(($D20-$F20)<=TABELAS!$B$23,MIN((VLOOKUP(MAX(0.01,$D20-$F20),TABELAS!$A$16:$C$20,2,TRUE)*($D20-$F20)-VLOOKUP(MAX(0.01,$D20-$F20),TABELAS!$A$16:$C$20,3,TRUE)),TABELAS!$B$24-TABELAS!$B$25*($D20-$F20)),0)),2))) | I20: =IF($D20="","",ROUND($D20*$F$2,2)) | J20: =IF($D20="","",ROUND($D20-$I20-$F20+$G20-$H20,2))
B21: TOTAL | C21: =COUNTA($B$5:$B$20)&" pessoa(s)" | D21: =SUM(D5:D20) | F21: =SUM(F5:F20) | G21: =SUM(G5:G20) | H21: =SUM(H5:H20) | I21: =SUM(I5:I20) | J21: =SUM(J5:J20)
A23: TERCEIROS — FOLHA À PARTE (SEM DESCONTO)
B24: NOME | D24: VALOR DO MÊS | E24: QUINZENA (40%) | F24: MENSAL (60%) | G24: PIX | H24: OBS
B25: RAIMUNDO MARIANO DA SILVA JUNIOR | D25: 4270 | E25: =IF($D25="","",ROUND($D25*$F$2,2)) | F25: =IF($D25="","",ROUND($D25-$E25,2)) | G25: raimundojunior100@gmail.com | H25: Vigia — terceiro, folha à parte, sem descontos
E26: =IF($D26="","",ROUND($D26*$F$2,2)) | F26: =IF($D26="","",ROUND($D26-$E26,2))
E27: =IF($D27="","",ROUND($D27*$F$2,2)) | F27: =IF($D27="","",ROUND($D27-$E27,2))
E28: =IF($D28="","",ROUND($D28*$F$2,2)) | F28: =IF($D28="","",ROUND($D28-$E28,2))
B29: TOTAL | D29: =SUM(D25:D28)

Sheet QUINZENA
A1: ="RELATÓRIO DE PAGAMENTO — QUINZENA — "&GERAL!$A$1
A2: ="Competência: "&GERAL!$B$2&" · Data: "&GERAL!$D$2&" · Quinzena: "&(GERAL!$F$2*100)&"% do bruto"
A4: Nº | B4: NOME | C4: FUNÇÃO | D4: TOTAL BRUTO | E4: QUINZENA | F4: AGÊNCIA / C/C | G4: PIX
A5: =IF(GERAL!$B5="","",GERAL!$A5) | B5: =IF(GERAL!$B5="","",GERAL!$B5) | C5: =IF(GERAL!$B5="","",GERAL!$C5) | D5: =IF(GERAL!$B5="","",GERAL!$D5) | E5: =IF(GERAL!$B5="","",GERAL!$I5) | F5: =IF(GERAL!$B5="","",GERAL!$K5) | G5: =IF(GERAL!$B5="","",GERAL!$L5)
A6: =IF(GERAL!$B6="","",GERAL!$A6) | B6: =IF(GERAL!$B6="","",GERAL!$B6) | C6: =IF(GERAL!$B6="","",GERAL!$C6) | D6: =IF(GERAL!$B6="","",GERAL!$D6) | E6: =IF(GERAL!$B6="","",GERAL!$I6) | F6: =IF(GERAL!$B6="","",GERAL!$K6) | G6: =IF(GERAL!$B6="","",GERAL!$L6)
A7: =IF(GERAL!$B7="","",GERAL!$A7) | B7: =IF(GERAL!$B7="","",GERAL!$B7) | C7: =IF(GERAL!$B7="","",GERAL!$C7) | D7: =IF(GERAL!$B7="","",GERAL!$D7) | E7: =IF(GERAL!$B7="","",GERAL!$I7) | F7: =IF(GERAL!$B7="","",GERAL!$K7) | G7: =IF(GERAL!$B7="","",GERAL!$L7)
A8: =IF(GERAL!$B8="","",GERAL!$A8) | B8: =IF(GERAL!$B8="","",GERAL!$B8) | C8: =IF(GERAL!$B8="","",GERAL!$C8) | D8: =IF(GERAL!$B8="","",GERAL!$D8) | E8: =IF(GERAL!$B8="","",GERAL!$I8) | F8: =IF(GERAL!$B8="","",GERAL!$K8) | G8: =IF(GERAL!$B8="","",GERAL!$L8)
A9: =IF(GERAL!$B9="","",GERAL!$A9) | B9: =IF(GERAL!$B9="","",GERAL!$B9) | C9: =IF(GERAL!$B9="","",GERAL!$C9) | D9: =IF(GERAL!$B9="","",GERAL!$D9) | E9: =IF(GERAL!$B9="","",GERAL!$I9) | F9: =IF(GERAL!$B9="","",GERAL!$K9) | G9: =IF(GERAL!$B9="","",GERAL!$L9)
A10: =IF(GERAL!$B10="","",GERAL!$A10) | B10: =IF(GERAL!$B10="","",GERAL!$B10) | C10: =IF(GERAL!$B10="","",GERAL!$C10) | D10: =IF(GERAL!$B10="","",GERAL!$D10) | E10: =IF(GERAL!$B10="","",GERAL!$I10) | F10: =IF(GERAL!$B10="","",GERAL!$K10) | G10: =IF(GERAL!$B10="","",GERAL!$L10)
A11: =IF(GERAL!$B11="","",GERAL!$A11) | B11: =IF(GERAL!$B11="","",GERAL!$B11) | C11: =IF(GERAL!$B11="","",GERAL!$C11) | D11: =IF(GERAL!$B11="","",GERAL!$D11) | E11: =IF(GERAL!$B11="","",GERAL!$I11) | F11: =IF(GERAL!$B11="","",GERAL!$K11) | G11: =IF(GERAL!$B11="","",GERAL!$L11)
A12: =IF(GERAL!$B12="","",GERAL!$A12) | B12: =IF(GERAL!$B12="","",GERAL!$B12) | C12: =IF(GERAL!$B12="","",GERAL!$C12) | D12: =IF(GERAL!$B12="","",GERAL!$D12) | E12: =IF(GERAL!$B12="","",GERAL!$I12) | F12: =IF(GERAL!$B12="","",GERAL!$K12) | G12: =IF(GERAL!$B12="","",GERAL!$L12)
A13: =IF(GERAL!$B13="","",GERAL!$A13) | B13: =IF(GERAL!$B13="","",GERAL!$B13) | C13: =IF(GERAL!$B13="","",GERAL!$C13) | D13: =IF(GERAL!$B13="","",GERAL!$D13) | E13: =IF(GERAL!$B13="","",GERAL!$I13) | F13: =IF(GERAL!$B13="","",GERAL!$K13) | G13: =IF(GERAL!$B13="","",GERAL!$L13)
A14: =IF(GERAL!$B14="","",GERAL!$A14) | B14: =IF(GERAL!$B14="","",GERAL!$B14) | C14: =IF(GERAL!$B14="","",GERAL!$C14) | D14: =IF(GERAL!$B14="","",GERAL!$D14) | E14: =IF(GERAL!$B14="","",GERAL!$I14) | F14: =IF(GERAL!$B14="","",GERAL!$K14) | G14: =IF(GERAL!$B14="","",GERAL!$L14)
A15: =IF(GERAL!$B15="","",GERAL!$A15) | B15: =IF(GERAL!$B15="","",GERAL!$B15) | C15: =IF(GERAL!$B15="","",GERAL!$C15) | D15: =IF(GERAL!$B15="","",GERAL!$D15) | E15: =IF(GERAL!$B15="","",GERAL!$I15) | F15: =IF(GERAL!$B15="","",GERAL!$K15) | G15: =IF(GERAL!$B15="","",GERAL!$L15)
A16: =IF(GERAL!$B16="","",GERAL!$A16) | B16: =IF(GERAL!$B16="","",GERAL!$B16) | C16: =IF(GERAL!$B16="","",GERAL!$C16) | D16: =IF(GERAL!$B16="","",GERAL!$D16) | E16: =IF(GERAL!$B16="","",GERAL!$I16) | F16: =IF(GERAL!$B16="","",GERAL!$K16) | G16: =IF(GERAL!$B16="","",GERAL!$L16)
... A20: =IF(GERAL!$B20="","",GERAL!$A20) | B20: =IF(GERAL!$B20="","",GERAL!$B20) | C20: =IF(GERAL!$B20="","",GERAL!$C20) | D20: =IF(GERAL!$B20="","",GERAL!$D20) | E20: =IF(GERAL!$B20="","",GERAL!$I20) | F20: =IF(GERAL!$B20="","",GERAL!$K20) | G20: =IF(GERAL!$B20="","",GERAL!$L20)
C21: TOTAL | D21: =SUM(D5:D20) | E21: =SUM(E5:E20)
A23: PROTOCOLO DE RECEBIMENTO — ASSINATURAS
A24: =IF(GERAL!$B5="","",GERAL!$B5&": _______________________________")
A25: =IF(GERAL!$B6="","",GERAL!$B6&": _______________________________")
A26: =IF(GERAL!$B7="","",GERAL!$B7&": _______________________________")
A27: =IF(GERAL!$B8="","",GERAL!$B8&": _______________________________")
A28: =IF(GERAL!$B9="","",GERAL!$B9&": _______________________________")
A29: =IF(GERAL!$B10="","",GERAL!$B10&": _______________________________")
A30: =IF(GERAL!$B11="","",GERAL!$B11&": _______________________________")
A31: =IF(GERAL!$B12="","",GERAL!$B12&": _______________________________")
A32: =IF(GERAL!$B13="","",GERAL!$B13&": _______________________________")
A33: =IF(GERAL!$B14="","",GERAL!$B14&": _______________________________")
A34: =IF(GERAL!$B15="","",GERAL!$B15&": _______________________________")
A35: =IF(GERAL!$B16="","",GERAL!$B16&": _______________________________")
... A39: =IF(GERAL!$B20="","",GERAL!$B20&": _______________________________")

Sheet MENSAL
A1: ="RELATÓRIO DE PAGAMENTO — FINAL DO MÊS — "&GERAL!$A$1
A2: ="Competência: "&GERAL!$B$2&" · Data: "&GERAL!$D$2
A4: Nº | B4: NOME | C4: FUNÇÃO | D4: TOTAL BRUTO | E4: QUINZENA | F4: INSS | G4: FAMÍLIA | H4: IRRF | I4: MENSAL (LÍQUIDO) | J4: AGÊNCIA / C/C | K4: PIX
A5: =IF(GERAL!$B5="","",GERAL!$A5) | B5: =IF(GERAL!$B5="","",GERAL!$B5) | C5: =IF(GERAL!$B5="","",GERAL!$C5) | D5: =IF(GERAL!$B5="","",GERAL!$D5) | E5: =IF(GERAL!$B5="","",GERAL!$I5) | F5: =IF(GERAL!$B5="","",GERAL!$F5) | G5: =IF(GERAL!$B5="","",GERAL!$G5) | H5: =IF(GERAL!$B5="","",GERAL!$H5) | I5: =IF(GERAL!$B5="","",GERAL!$J5) | J5: =IF(GERAL!$B5="","",GERAL!$K5) | K5: =IF(GERAL!$B5="","",GERAL!$L5)
A6: =IF(GERAL!$B6="","",GERAL!$A6) | B6: =IF(GERAL!$B6="","",GERAL!$B6) | C6: =IF(GERAL!$B6="","",GERAL!$C6) | D6: =IF(GERAL!$B6="","",GERAL!$D6) | E6: =IF(GERAL!$B6="","",GERAL!$I6) | F6: =IF(GERAL!$B6="","",GERAL!$F6) | G6: =IF(GERAL!$B6="","",GERAL!$G6) | H6: =IF(GERAL!$B6="","",GERAL!$H6) | I6: =IF(GERAL!$B6="","",GERAL!$J6) | J6: =IF(GERAL!$B6="","",GERAL!$K6) | K6: =IF(GERAL!$B6="","",GERAL!$L6)
A7: =IF(GERAL!$B7="","",GERAL!$A7) | B7: =IF(GERAL!$B7="","",GERAL!$B7) | C7: =IF(GERAL!$B7="","",GERAL!$C7) | D7: =IF(GERAL!$B7="","",GERAL!$D7) | E7: =IF(GERAL!$B7="","",GERAL!$I7) | F7: =IF(GERAL!$B7="","",GERAL!$F7) | G7: =IF(GERAL!$B7="","",GERAL!$G7) | H7: =IF(GERAL!$B7="","",GERAL!$H7) | I7: =IF(GERAL!$B7="","",GERAL!$J7) | J7: =IF(GERAL!$B7="","",GERAL!$K7) | K7: =IF(GERAL!$B7="","",GERAL!$L7)
A8: =IF(GERAL!$B8="","",GERAL!$A8) | B8: =IF(GERAL!$B8="","",GERAL!$B8) | C8: =IF(GERAL!$B8="","",GERAL!$C8) | D8: =IF(GERAL!$B8="","",GERAL!$D8) | E8: =IF(GERAL!$B8="","",GERAL!$I8) | F8: =IF(GERAL!$B8="","",GERAL!$F8) | G8: =IF(GERAL!$B8="","",GERAL!$G8) | H8: =IF(GERAL!$B8="","",GERAL!$H8) | I8: =IF(GERAL!$B8="","",GERAL!$J8) | J8: =IF(GERAL!$B8="","",GERAL!$K8) | K8: =IF(GERAL!$B8="","",GERAL!$L8)
A9: =IF(GERAL!$B9="","",GERAL!$A9) | B9: =IF(GERAL!$B9="","",GERAL!$B9) | C9: =IF(GERAL!$B9="","",GERAL!$C9) | D9: =IF(GERAL!$B9="","",GERAL!$D9) | E9: =IF(GERAL!$B9="","",GERAL!$I9) | F9: =IF(GERAL!$B9="","",GERAL!$F9) | G9: =IF(GERAL!$B9="","",GERAL!$G9) | H9: =IF(GERAL!$B9="","",GERAL!$H9) | I9: =IF(GERAL!$B9="","",GERAL!$J9) | J9: =IF(GERAL!$B9="","",GERAL!$K9) | K9: =IF(GERAL!$B9="","",GERAL!$L9)
A10: =IF(GERAL!$B10="","",GERAL!$A10) | B10: =IF(GERAL!$B10="","",GERAL!$B10) | C10: =IF(GERAL!$B10="","",GERAL!$C10) | D10: =IF(GERAL!$B10="","",GERAL!$D10) | E10: =IF(GERAL!$B10="","",GERAL!$I10) | F10: =IF(GERAL!$B10="","",GERAL!$F10) | G10: =IF(GERAL!$B10="","",GERAL!$G10) | H10: =IF(GERAL!$B10="","",GERAL!$H10) | I10: =IF(GERAL!$B10="","",GERAL!$J10) | J10: =IF(GERAL!$B10="","",GERAL!$K10) | K10: =IF(GERAL!$B10="","",GERAL!$L10)
A11: =IF(GERAL!$B11="","",GERAL!$A11) | B11: =IF(GERAL!$B11="","",GERAL!$B11) | C11: =IF(GERAL!$B11="","",GERAL!$C11) | D11: =IF(GERAL!$B11="","",GERAL!$D11) | E11: =IF(GERAL!$B11="","",GERAL!$I11) | F11: =IF(GERAL!$B11="","",GERAL!$F11) | G11: =IF(GERAL!$B11="","",GERAL!$G11) | H11: =IF(GERAL!$B11="","",GERAL!$H11) | I11: =IF(GERAL!$B11="","",GERAL!$J11) | J11: =IF(GERAL!$B11="","",GERAL!$K11) | K11: =IF(GERAL!$B11="","",GERAL!$L11)
A12: =IF(GERAL!$B12="","",GERAL!$A12) | B12: =IF(GERAL!$B12="","",GERAL!$B12) | C12: =IF(GERAL!$B12="","",GERAL!$C12) | D12: =IF(GERAL!$B12="","",GERAL!$D12) | E12: =IF(GERAL!$B12="","",GERAL!$I12) | F12: =IF(GERAL!$B12="","",GERAL!$F12) | G12: =IF(GERAL!$B12="","",GERAL!$G12) | H12: =IF(GERAL!$B12="","",GERAL!$H12) | I12: =IF(GERAL!$B12="","",GERAL!$J12) | J12: =IF(GERAL!$B12="","",GERAL!$K12) | K12: =IF(GERAL!$B12="","",GERAL!$L12)
A13: =IF(GERAL!$B13="","",GERAL!$A13) | B13: =IF(GERAL!$B13="","",GERAL!$B13) | C13: =IF(GERAL!$B13="","",GERAL!$C13) | D13: =IF(GERAL!$B13="","",GERAL!$D13) | E13: =IF(GERAL!$B13="","",GERAL!$I13) | F13: =IF(GERAL!$B13="","",GERAL!$F13) | G13: =IF(GERAL!$B13="","",GERAL!$G13) | H13: =IF(GERAL!$B13="","",GERAL!$H13) | I13: =IF(GERAL!$B13="","",GERAL!$J13) | J13: =IF(GERAL!$B13="","",GERAL!$K13) | K13: =IF(GERAL!$B13="","",GERAL!$L13)
A14: =IF(GERAL!$B14="","",GERAL!$A14) | B14: =IF(GERAL!$B14="","",GERAL!$B14) | C14: =IF(GERAL!$B14="","",GERAL!$C14) | D14: =IF(GERAL!$B14="","",GERAL!$D14) | E14: =IF(GERAL!$B14="","",GERAL!$I14) | F14: =IF(GERAL!$B14="","",GERAL!$F14) | G14: =IF(GERAL!$B14="","",GERAL!$G14) | H14: =IF(GERAL!$B14="","",GERAL!$H14) | I14: =IF(GERAL!$B14="","",GERAL!$J14) | J14: =IF(GERAL!$B14="","",GERAL!$K14) | K14: =IF(GERAL!$B14="","",GERAL!$L14)
A15: =IF(GERAL!$B15="","",GERAL!$A15) | B15: =IF(GERAL!$B15="","",GERAL!$B15) | C15: =IF(GERAL!$B15="","",GERAL!$C15) | D15: =IF(GERAL!$B15="","",GERAL!$D15) | E15: =IF(GERAL!$B15="","",GERAL!$I15) | F15: =IF(GERAL!$B15="","",GERAL!$F15) | G15: =IF(GERAL!$B15="","",GERAL!$G15) | H15: =IF(GERAL!$B15="","",GERAL!$H15) | I15: =IF(GERAL!$B15="","",GERAL!$J15) | J15: =IF(GERAL!$B15="","",GERAL!$K15) | K15: =IF(GERAL!$B15="","",GERAL!$L15)
A16: =IF(GERAL!$B16="","",GERAL!$A16) | B16: =IF(GERAL!$B16="","",GERAL!$B16) | C16: =IF(GERAL!$B16="","",GERAL!$C16) | D16: =IF(GERAL!$B16="","",GERAL!$D16) | E16: =IF(GERAL!$B16="","",GERAL!$I16) | F16: =IF(GERAL!$B16="","",GERAL!$F16) | G16: =IF(GERAL!$B16="","",GERAL!$G16) | H16: =IF(GERAL!$B16="","",GERAL!$H16) | I16: =IF(GERAL!$B16="","",GERAL!$J16) | J16: =IF(GERAL!$B16="","",GERAL!$K16) | K16: =IF(GERAL!$B16="","",GERAL!$L16)
... A20: =IF(GERAL!$B20="","",GERAL!$A20) | B20: =IF(GERAL!$B20="","",GERAL!$B20) | C20: =IF(GERAL!$B20="","",GERAL!$C20) | D20: =IF(GERAL!$B20="","",GERAL!$D20) | E20: =IF(GERAL!$B20="","",GERAL!$I20) | F20: =IF(GERAL!$B20="","",GERAL!$F20) | G20: =IF(GERAL!$B20="","",GERAL!$G20) | H20: =IF(GERAL!$B20="","",GERAL!$H20) | I20: =IF(GERAL!$B20="","",GERAL!$J20) | J20: =IF(GERAL!$B20="","",GERAL!$K20) | K20: =IF(GERAL!$B20="","",GERAL!$L20)
C21: TOTAL | E21: =SUM(E5:E20) | F21: =SUM(F5:F20) | G21: =SUM(G5:G20) | H21: =SUM(H5:H20) | I21: =SUM(I5:I20)
A23: ="TERMO DE QUITAÇÃO — Declaramos para os devidos fins que recebemos as importâncias líquidas discriminadas na tabela acima, referentes ao mês de "&GERAL!$B$2&", nada mais tendo a reclamar quanto aos valores aqui expressos."
A26: ASSINATURAS:
A27: =IF(GERAL!$B5="","",GERAL!$B5&": _______________________________________________")
A28: =IF(GERAL!$B6="","",GERAL!$B6&": _______________________________________________")
A29: =IF(GERAL!$B7="","",GERAL!$B7&": _______________________________________________")
A30: =IF(GERAL!$B8="","",GERAL!$B8&": _______________________________________________")
A31: =IF(GERAL!$B9="","",GERAL!$B9&": _______________________________________________")
A32: =IF(GERAL!$B10="","",GERAL!$B10&": _______________________________________________")
A33: =IF(GERAL!$B11="","",GERAL!$B11&": _______________________________________________")
A34: =IF(GERAL!$B12="","",GERAL!$B12&": _______________________________________________")
A35: =IF(GERAL!$B13="","",GERAL!$B13&": _______________________________________________")
A36: =IF(GERAL!$B14="","",GERAL!$B14&": _______________________________________________")
A37: =IF(GERAL!$B15="","",GERAL!$B15&": _______________________________________________")
A38: =IF(GERAL!$B16="","",GERAL!$B16&": _______________________________________________")
... A42: =IF(GERAL!$B20="","",GERAL!$B20&": _______________________________________________")

Sheet PRODUÇÃO
A1: ="RELATÓRIO DE PRODUÇÃO — "&GERAL!$A$1
A2: ="Competência: "&GERAL!$B$2&" · Data: "&GERAL!$D$2
A4: Nº | B4: NOME | C4: OBRAS | D4: VALOR/OBRA | E4: LIMP/LUBRIF. | F4: SÁBADO | G4: FERIADO | H4: AJUDA DE CUSTO | I4: ADIANTAMENTO | J4: GRATIFICAÇÃO | K4: PRODUÇÃO | L4: A PAGAR | M4: AGÊNCIA / C/C | N4: PIX
A5: =IF(GERAL!$B5="","",GERAL!$A5) | B5: =IF(GERAL!$B5="","",GERAL!$B5) | C5: 41 | D5: 20 | E5: 100 | F5: 50 | K5: =IF($B5="","",ROUND(C5*D5+E5+F5+G5+H5,2)) | L5: =IF($B5="","",ROUND(K5+J5-I5,2)) | M5: =IF(GERAL!$B5="","",GERAL!$K5) | N5: =IF(GERAL!$B5="","",GERAL!$L5)
A6: =IF(GERAL!$B6="","",GERAL!$A6) | B6: =IF(GERAL!$B6="","",GERAL!$B6) | C6: 49 | D6: 20 | E6: 200 | F6: 50 | K6: =IF($B6="","",ROUND(C6*D6+E6+F6+G6+H6,2)) | L6: =IF($B6="","",ROUND(K6+J6-I6,2)) | M6: =IF(GERAL!$B6="","",GERAL!$K6) | N6: =IF(GERAL!$B6="","",GERAL!$L6)
A7: =IF(GERAL!$B7="","",GERAL!$A7) | B7: =IF(GERAL!$B7="","",GERAL!$B7) | C7: 50 | D7: 20 | E7: 100 | F7: 50 | K7: =IF($B7="","",ROUND(C7*D7+E7+F7+G7+H7,2)) | L7: =IF($B7="","",ROUND(K7+J7-I7,2)) | M7: =IF(GERAL!$B7="","",GERAL!$K7) | N7: =IF(GERAL!$B7="","",GERAL!$L7)
A8: =IF(GERAL!$B8="","",GERAL!$A8) | B8: =IF(GERAL!$B8="","",GERAL!$B8) | C8: 62 | D8: 20 | E8: 100 | F8: 50 | K8: =IF($B8="","",ROUND(C8*D8+E8+F8+G8+H8,2)) | L8: =IF($B8="","",ROUND(K8+J8-I8,2)) | M8: =IF(GERAL!$B8="","",GERAL!$K8) | N8: =IF(GERAL!$B8="","",GERAL!$L8)
A9: =IF(GERAL!$B9="","",GERAL!$A9) | B9: =IF(GERAL!$B9="","",GERAL!$B9) | C9: 62 | D9: 20 | E9: 100 | F9: 50 | K9: =IF($B9="","",ROUND(C9*D9+E9+F9+G9+H9,2)) | L9: =IF($B9="","",ROUND(K9+J9-I9,2)) | M9: =IF(GERAL!$B9="","",GERAL!$K9) | N9: =IF(GERAL!$B9="","",GERAL!$L9)
A10: =IF(GERAL!$B10="","",GERAL!$A10) | B10: =IF(GERAL!$B10="","",GERAL!$B10) | C10: 44 | D10: 20 | E10: 100 | F10: 50 | K10: =IF($B10="","",ROUND(C10*D10+E10+F10+G10+H10,2)) | L10: =IF($B10="","",ROUND(K10+J10-I10,2)) | M10: =IF(GERAL!$B10="","",GERAL!$K10) | N10: =IF(GERAL!$B10="","",GERAL!$L10)
A11: =IF(GERAL!$B11="","",GERAL!$A11) | B11: =IF(GERAL!$B11="","",GERAL!$B11) | C11: 62 | D11: 20 | E11: 100 | F11: 50 | K11: =IF($B11="","",ROUND(C11*D11+E11+F11+G11+H11,2)) | L11: =IF($B11="","",ROUND(K11+J11-I11,2)) | M11: =IF(GERAL!$B11="","",GERAL!$K11) | N11: =IF(GERAL!$B11="","",GERAL!$L11)
A12: =IF(GERAL!$B12="","",GERAL!$A12) | B12: =IF(GERAL!$B12="","",GERAL!$B12) | C12: 50 | D12: 20 | E12: 100 | F12: 50 | K12: =IF($B12="","",ROUND(C12*D12+E12+F12+G12+H12,2)) | L12: =IF($B12="","",ROUND(K12+J12-I12,2)) | M12: =IF(GERAL!$B12="","",GERAL!$K12) | N12: =IF(GERAL!$B12="","",GERAL!$L12)
C21: TOTAL | I21: =SUM(I5:I20) | J21: =SUM(J5:J20) | K21: =SUM(K5:K20) | L21: =SUM(L5:L20)
A22: A PAGAR = PRODUÇÃO + GRATIFICAÇÃO − ADIANTAMENTO (o adiantamento é o que a pessoa já recebeu no mês)
A23: ="TERMO DE QUITAÇÃO — Declaramos para os devidos fins que recebemos as importâncias de produção discriminadas na tabela acima, referentes ao mês de "&GERAL!$B$2&", nada mais tendo a reclamar quanto aos valores aqui expressos."
A26: ASSINATURAS:
A27: =IF(GERAL!$B5="","",GERAL!$B5&": _______________________________________________")
A28: =IF(GERAL!$B6="","",GERAL!$B6&": _______________________________________________")
A29: =IF(GERAL!$B7="","",GERAL!$B7&": _______________________________________________")
A30: =IF(GERAL!$B8="","",GERAL!$B8&": _______________________________________________")
A31: =IF(GERAL!$B9="","",GERAL!$B9&": _______________________________________________")
A32: =IF(GERAL!$B10="","",GERAL!$B10&": _______________________________________________")
A33: =IF(GERAL!$B11="","",GERAL!$B11&": _______________________________________________")
A34: =IF(GERAL!$B12="","",GERAL!$B12&": _______________________________________________")

Sheet VENDAS
A1: ="RELATÓRIO DE VENDAS E COMISSÕES — "&GERAL!$A$1
A2: ="Competência: "&GERAL!$B$2&" · Data: "&GERAL!$D$2
A4: VENDEDORES DA FOLHA (comissão é pagamento à parte do salário) | C4: COMISSÃO = 0,5% DO VALOR VENDIDO (calcula sozinha)
A5: Nº | B5: NOME | C5: VALOR DAS OBRAS | D5: COMISSÃO | E5: AGÊNCIA / C/C | F5: PIX
A6: =IF(GERAL!$B14="","",GERAL!$A14) | B6: =IF(GERAL!$B14="","",GERAL!$B14) | C6: 1300832.4 | D6: =IF($C6="","",ROUND($C6*0.005,2)) | E6: =IF(GERAL!$B14="","",GERAL!$K14) | F6: =IF(GERAL!$B14="","",GERAL!$L14)
D7: =IF($C7="","",ROUND($C7*0.005,2))
D8: =IF($C8="","",ROUND($C8*0.005,2))
D9: =IF($C9="","",ROUND($C9*0.005,2))
C10: TOTAL VENDAS | D10: =SUM(D6:D9)
A36: Regra: COMISSÃO = 0,5% × VALOR VENDIDO (a coluna COMISSÃO calcula sozinha).

Sheet RESUMO
A1: ="RESUMO DO MÊS — "&GERAL!$A$1
A3: Competência | B3: =GERAL!$B$2
A4: Pessoas na folha | B4: =COUNTA(GERAL!$B$5:$B$20)
A6: Salários — Quinzena | B6: =GERAL!$I$21
A7: Salários — Mensal (líquido) | B7: =GERAL!$J$21
A8: SUBTOTAL FOLHA | B8: =B6+B7
A9: Produção (a pagar) | B9: ='PRODUÇÃO'!$L$21
A10: Vendas (comissões) | B10: =VENDAS!$D$10
A11: Terceiros (folha à parte) | B11: =GERAL!$D$29
A12: INSS retido (recolher) | B12: =GERAL!$F$21
A13: IRRF retido (recolher) | B13: =GERAL!$H$21
A14: Salário-família pago | B14: =GERAL!$G$21
A16: TOTAL GERAL DO MÊS | B16: =B8+B9+B10+B11
A18: Tudo aqui é automático — puxa do GERAL, PRODUÇÃO e VENDAS.

Sheet TABELAS
A1: TABELAS OFICIAIS 2026 — NÃO MEXER (as fórmulas usam estes valores)
A2: Fontes: Portaria Interministerial MPS/MF nº 13/2026 (INSS e salário-família) · Lei 15.270/2025 + tabela da Receita Federal (IRRF). Confirme com o contador.
A4: INSS — a partir de (R$) | B4: Alíquota | C4: Parcela a deduzir
A5: 0 | B5: 0.075 | C5: 0
A6: 1621.01 | B6: 0.09 | C6: 24.32
A7: 2902.85 | B7: 0.12 | C7: 111.4
A8: 4354.28 | B8: 0.14 | C8: 198.49
A10: Teto do INSS (máx. de contribuição) | B10: 8475.55
A12: Salário-família — cota por filho (até 14 anos) | B12: 67.54
A13: Salário-família — só para bruto até | B13: 1980.38
A15: IRRF — base a partir de (R$) | B15: Alíquota | C15: Parcela a deduzir
A16: 0 | B16: 0 | C16: 0
A17: 2428.81 | B17: 0.075 | C17: 182.16
A18: 2826.66 | B18: 0.15 | C18: 394.16
A19: 3751.06 | B19: 0.225 | C19: 675.49
A20: 4664.69 | B20: 0.275 | C20: 908.73
A22: IR — isento até (salário bruto) | B22: 5000
A23: IR — desconto gradual até (base) | B23: 7350
A24: IR — parcela fixa da redução | B24: 978.62
A25: IR — coeficiente da redução | B25: 0.133145
A27: Salário mínimo 2026 | B27: 1621
